election_campaign/__init__.py
election_campaign/citizen_sentiment.py
election_campaign/complaints_areas.py
election_campaign/general_trends.py
election_campaign/politicians_reputation.py
election_campaign-0.0.1.dist-info/LICENSE
election_campaign-0.0.1.dist-info/METADATA
election_campaign-0.0.1.dist-info/WHEEL
election_campaign-0.0.1.dist-info/top_level.txt
election_campaign-0.0.1.dist-info/RECORD
