Metadata-Version: 2.1
Name: election-campaign
Version: 0.0.1
Summary: This library serves as an extension of and for the election campaign API, https://research-questions-api.herokuapp.com/redoc.
Home-page: https://github.com/dub-em/Election-Campaign-Application.git
Author: Dubem
Author-email: michaeligbomezie@gmail.com
Keywords: ["election-campaign","citizens-voice","governance","Dubem"]
Classifier: Programming Language :: Python :: 3
Classifier: License :: OSI Approved :: MIT License
Classifier: Operating System :: OS Independent
License-File: LICENSE
